Workbook

Sheet 1_估值快照
A1: 指标 | B1: 数值 | C1: 来源 | D1: 备注
A2: 股票代码 | B2: 600519.SH | C2: eastmoney
A3: 股票名称 | B3: 贵州茅台 | C3: eastmoney
A4: PE(TTM) | B4: 27.5 | C4: eastmoney | D4: 市盈率(滚动 12 月)
A5: PE(静态) | B5: 28.3 | C5: eastmoney | D5: 市盈率(去年)
A6: PB | B6: 8.9 | C6: eastmoney | D6: 市净率
A7: 市值(亿元) | B7: 16500 | C7: eastmoney
A8: 行业 PE | B8: 32.1 | C8: eastmoney | D8: 对照基准
A9: 相对估值(PE_TTM/行业_PE) | B9: =B4/B8 | C9: 公式 | D9: 本表内公式
A10: 一致预期 EPS 2025E | B10: 68.5 | C10: iwencai
A11: 买入/持有/卖出 | B11: 28/8/1 | C11: iwencai | D11: 37 家覆盖
A12: 目标价中位数 | B12: 1850 | C12: iwencai

Sheet 2_财报三表
A1: 科目 | B1: 金额(元) | C1: 占比 | D1: 来源
A2: 总资产 | B2: 285000000000 | C2: =B2/$B$2 | D2: mootdx
A3: 总负债 | B3: 41800000000 | C3: =B3/$B$2 | D3: mootdx
A4: 股东权益 | B4: 243000000000 | C4: =B4/$B$2 | D4: mootdx
A5: 流动资产 | B5: 210000000000 | C5: =B5/$B$2 | D5: mootdx
A6: 流动负债 | B6: 38500000000 | C6: =B6/$B$2 | D6: mootdx
A7: 现金及等价物 | B7: 14500000000 | C7: =B7/$B$2 | D7: mootdx
A8: 存货 | B8: 42000000000 | C8: =B8/$B$2 | D8: mootdx
A9: 应收账款 | B9: 1200000000 | C9: =B9/$B$2 | D9: mootdx
A10: 营业收入 | B10: 174000000000 | C10: =B10/$B$2 | D10: mootdx
A11: 营业成本 | B11: 43000000000 | C11: =B11/$B$2 | D11: mootdx
A12: 毛利 | B12: 131000000000 | C12: =B12/$B$2 | D12: mootdx
A13: 营业费用 | B13: 18000000000 | C13: =B13/$B$2 | D13: mootdx
... A19: 自由现金流 | B19: 56500000000 | C19: =B19/$B$2 | D19: mootdx
A21: === 关键比率（自动算）===
A22: 资产负债率 | B22: =B3/B2
A23: 流动比率 | B23: =B5/B6
A24: 毛利率 | B24: =B12/B10
A25: 净利率 | B25: =B15/B10

Sheet 3_季报关键指标
A1: 指标 | B1: 数值 | C1: 同比 | D1: 来源 | F1: 上季度对照（模拟）
A2: 营收同比 | B2: 0.182 | C2: =B2-G2 | D2: mootdx | G2: 0.15
A3: 净利同比 | B3: 0.247 | C3: =B3-G3 | D3: mootdx | G3: 0.19
A4: 毛利率 | B4: 0.753 | C4: =B4-G4 | D4: mootdx | G4: 0.74
A5: ROE | B5: 0.265 | C5: =B5-G5 | D5: mootdx | G5: 0.25
A6: ROA | B6: 0.227 | C6: =B6-G6 | D6: mootdx | G6: 0.215
A7: 资产负债率 | B7: 0.147 | C7: =B7-G7 | D7: mootdx | G7: 0.152
A8: 流动比率 | B8: 5.45 | C8: =(B8-G8)/G8 | D8: mootdx | G8: 5.2
A9: 速动比率 | B9: 4.36 | C9: =(B9-G9)/G9 | D9: mootdx | G9: 4.1
A10: 存货周转天数 | B10: 1240 | C10: =(B10-G10)/G10 | D10: mootdx | G10: 1320
A11: 应收周转天数 | B11: 5 | C11: =(B11-G11)/G11 | D11: mootdx | G11: 6
A12: 基本 EPS | B12: 12.9 | C12: =(B12-G12)/G12 | D12: mootdx | G12: 11.5
A13: 每股净资产 | B13: 193.5 | C13: =(B13-G13)/G13 | D13: mootdx | G13: 185
A14: 每股经营性现金流 | B14: 5.45 | C14: =(B14-G14)/G14 | D14: mootdx | G14: 4.8

Sheet 4_资金流与持仓
A1: 指标 | B1: 数值 | C1: 来源
A2: 北向净买入(5 日, 亿元) | B2: 12 | C2: eastmoney
A3: 北向净买入(20 日, 亿元) | B3: 34.5 | C3: eastmoney
A4: 北向持股(万股) | B4: 9850 | C4: eastmoney
A5: 北向持股比例 | B5: 0.0784 | C5: eastmoney
A7: === 财务健康度评分（跨 sheet）===
A8: ROE 贡献（40%） | B8: ='3_季报关键指标'!B5*0.4
A9: 资产负债率反向贡献（30%） | B9: =(1-'3_季报关键指标'!B7)*0.3
A10: 毛利率贡献（20%） | B10: ='3_季报关键指标'!B4*0.2
A11: 流动比率归一贡献（10%） | B11: =MIN('3_季报关键指标'!B8/10,1)*0.1
A12: 财务健康度总分 | B12: =SUM(B8:B11)

Sheet 5_投资分析
A1: 维度 | B1: 评分 | C1: 权重 | D1: 加权得分 | E1: 来源
A2: 估值合理性 | B2: ='1_估值快照'!B9 | C2: 0.2 | D2: =B2*C2 | E2: PE/行业 PE
A3: 财务健康 | B3: ='4_资金流与持仓'!B12 | C3: 0.3 | D3: =B3*C3 | E3: Sheet 4 总分
A4: 业绩同比 | B4: ='3_季报关键指标'!C2 | C4: 0.2 | D4: =B4*C4 | E4: Sheet 3 营收同比差
A5: 资金面（北向） | B5: ='4_资金流与持仓'!B5 | C5: 0.15 | D5: =B5*C5 | E5: Sheet 4 持股比例
A6: 分析师一致预期 | B6: ='1_估值快照'!B11 | C6: 0.15 | D6: =B6*C6 | E6: 目标价中位数 / 当前价
A7: 综合得分 | B7: =SUM(D2:D6)
A8: 投资建议 | B8: =IF(B7>0.6,"强烈推荐",IF(B7>0.4,"推荐",IF(B7>0.2,"中性","回避")))
